cpadapter/__init__.py
cpadapter/adapter_classes.py
cpadapter/conformal_adaptor.py
cpadapter/performance_measures.py
cpadapter/utils.py
cpadapter/visualization.py
cpadapter-0.1.2.dist-info/WHEEL
cpadapter-0.1.2.dist-info/METADATA
cpadapter-0.1.2.dist-info/RECORD
