Metadata-Version: 2.1
Name: cpadapter
Version: 0.1.2
Summary: This package adapts different models in order to create confidence intervals using conformal prediction
Author: mjesusugarte
Author-email: maria.jesus@spikelab.xyz
Requires-Python: >=3.7,<4.0
Classifier: Programming Language :: Python :: 3
Classifier: Programming Language :: Python :: 3.7
Classifier: Programming Language :: Python :: 3.8
Classifier: Programming Language :: Python :: 3.9
Requires-Dist: lightgbm (>=3.1,<4.0)
Requires-Dist: matplotlib (>=3.0,<4.0)
Requires-Dist: nonconformist (>=2.1.0,<3.0.0)
Requires-Dist: numpy (>=1.19,<2.0)
Requires-Dist: pandas (>=1.1,<2.0)
Requires-Dist: seaborn (>=0.11,<0.12)
Requires-Dist: sklearn (>=0.0,<0.1)
Requires-Dist: typing (>=3.7,<4.0)
